deprecated-stubs/METADATA.toml
deprecated-stubs/__init__.pyi
deprecated-stubs/classic.pyi
deprecated-stubs/sphinx.pyi
types_Deprecated-1.2.9.1.dist-info/METADATA
types_Deprecated-1.2.9.1.dist-info/WHEEL
types_Deprecated-1.2.9.1.dist-info/top_level.txt
types_Deprecated-1.2.9.1.dist-info/RECORD
